<?xml version="1.0" encoding="utf-8"?>
<Resources Culture="ru-RU">
	<Group Type="String">
		<Items>
			<Item Name="Caption" Value="DefaultLics" />
			<Item Name="Columns.UsrCash.Caption" Value="Cash" />
			<Item Name="Columns.UsrDocuments.Caption" Value="Documents" />
			<Item Name="Columns.UsrDocumentsUA.Caption" Value="Документи" />
			<Item Name="Columns.UsrDoorsDoors.Caption" Value="DoorsDoors" />
			<Item Name="Columns.UsrDoorsWarehouse.Caption" Value="DoorsWarehouse" />
			<Item Name="Columns.UsrNonCash.Caption" Value="NonCash" />
			<Item Name="Columns.UsrParcel.Caption" Value="Parcel" />
			<Item Name="Columns.UsrRecipient.Caption" Value="Recipient" />
			<Item Name="Columns.UsrSender.Caption" Value="Sender" />
			<Item Name="Columns.UsrThirdPerson.Caption" Value="ThirdPerson" />
			<Item Name="Columns.UsrWarehouseDoors.Caption" Value="WarehouseDoors" />
			<Item Name="Columns.UsrWarehousePostomat.Caption" Value="WarehousePostomat" />
			<Item Name="Columns.UsrWarehouseWarehouse.Caption" Value="WarehouseWarehouse" />
		</Items>
	</Group>
</Resources>